{
  "status": "idle",
  "session_id": "SESSION-20260716-92A106",
  "mission_id": "MIS-20260716-566472",
  "progress": 100,
  "current_thought": "Session completed · published=5 extracted=5 validated=5 rejected=0 docs=142 entity=Corporate Governance Improving Corporate Governance in India- Related ...",
  "current_task": "Idle",
  "last_learned": "Corporate Governance Improving Corporate Governance in India- Related ...",
  "updated_at": "2026-07-16T03:52:26+00:00",
  "execution_model": "github_actions",
  "last_error": null
}
