{
  "sources": {
    "SRC-000005": {
      "source_id": "SRC-000005",
      "attempts": 4,
      "successes": 4,
      "failures": 0,
      "documents_yielded": 2,
      "rows_yielded": 0,
      "duplicates": 1,
      "total_latency_ms": 361.80000000000007,
      "confidence_sum": 0.0,
      "confidence_n": 0,
      "backoff_level": 0,
      "disabled_until": null,
      "success_rate": 1.0,
      "avg_latency_ms": 90.5,
      "duplicate_rate": 0.3333
    },
    "SRC-000006": {
      "source_id": "SRC-000006",
      "attempts": 4,
      "successes": 4,
      "failures": 0,
      "documents_yielded": 2,
      "rows_yielded": 0,
      "duplicates": 0,
      "total_latency_ms": 360.40000000000003,
      "confidence_sum": 0.0,
      "confidence_n": 0,
      "backoff_level": 0,
      "disabled_until": null,
      "success_rate": 1.0,
      "avg_latency_ms": 90.1,
      "duplicate_rate": 0.0
    },
    "SRC-000001": {
      "source_id": "SRC-000001",
      "attempts": 4,
      "successes": 4,
      "failures": 0,
      "documents_yielded": 0,
      "rows_yielded": 0,
      "duplicates": 0,
      "total_latency_ms": 668.0,
      "confidence_sum": 0.0,
      "confidence_n": 0,
      "backoff_level": 0,
      "disabled_until": null,
      "success_rate": 1.0,
      "avg_latency_ms": 167.0,
      "duplicate_rate": 0.0
    },
    "SRC-000004": {
      "source_id": "SRC-000004",
      "attempts": 4,
      "successes": 4,
      "failures": 0,
      "documents_yielded": 4,
      "rows_yielded": 1,
      "duplicates": 0,
      "total_latency_ms": 1492.9999999999998,
      "confidence_sum": 0.0,
      "confidence_n": 0,
      "backoff_level": 0,
      "disabled_until": null,
      "success_rate": 1.0,
      "avg_latency_ms": 373.2,
      "duplicate_rate": 0.0
    },
    "SRC-CROSSREF": {
      "source_id": "SRC-CROSSREF",
      "attempts": 4,
      "successes": 4,
      "failures": 0,
      "documents_yielded": 10,
      "rows_yielded": 3,
      "duplicates": 0,
      "total_latency_ms": 1890.0,
      "confidence_sum": 0.0,
      "confidence_n": 0,
      "backoff_level": 0,
      "disabled_until": null,
      "success_rate": 1.0,
      "avg_latency_ms": 472.5,
      "duplicate_rate": 0.0
    },
    "SRC-OPENALEX": {
      "source_id": "SRC-OPENALEX",
      "attempts": 4,
      "successes": 4,
      "failures": 0,
      "documents_yielded": 9,
      "rows_yielded": 1,
      "duplicates": 0,
      "total_latency_ms": 4717.8,
      "confidence_sum": 0.0,
      "confidence_n": 0,
      "backoff_level": 0,
      "disabled_until": null,
      "success_rate": 1.0,
      "avg_latency_ms": 1179.5,
      "duplicate_rate": 0.0
    },
    "SRC-000007": {
      "source_id": "SRC-000007",
      "attempts": 4,
      "successes": 4,
      "failures": 0,
      "documents_yielded": 2,
      "rows_yielded": 0,
      "duplicates": 0,
      "total_latency_ms": 6348.199999999999,
      "confidence_sum": 0.0,
      "confidence_n": 0,
      "backoff_level": 0,
      "disabled_until": null,
      "success_rate": 1.0,
      "avg_latency_ms": 1587.0,
      "duplicate_rate": 0.0
    }
  }
}
